Metadata-Version: 1.0
Name: distributions-gj
Version: 0.1
Summary: Gaussian distributions
Home-page: UNKNOWN
Author: Gabor Jenei
Author-email: jeneigabor14@gmail.com
License: UNKNOWN
Platform: UNKNOWN
